MANIFEST.in
README
setup.py
bin/quickclassdiagram
bin/quickclassdiagramgtk
quickdiagrams/__init__.py
quickdiagrams/genqd.py
quickdiagrams/main.py
quickdiagrams/pac_parser.py
quickdiagrams/parser.py
quickdiagrams.egg-info/PKG-INFO
quickdiagrams.egg-info/SOURCES.txt
quickdiagrams.egg-info/dependency_links.txt
quickdiagrams.egg-info/requires.txt
quickdiagrams.egg-info/top_level.txt
quickdiagrams/gtkclient/COPYING
quickdiagrams/gtkclient/__init__.py
quickdiagrams/gtkclient/__init__.pyc
quickdiagrams/gtkclient/dialogs.py
quickdiagrams/gtkclient/dialogs.pyc
quickdiagrams/gtkclient/drawing_thread.py
quickdiagrams/gtkclient/drawing_thread.pyc
quickdiagrams/gtkclient/gtkcodebuffer.py
quickdiagrams/gtkclient/gtkcodebuffer.pyc
quickdiagrams/gtkclient/lifoqueue.py
quickdiagrams/gtkclient/lifoqueue.pyc
quickdiagrams/gtkclient/logo.ico
quickdiagrams/gtkclient/test.py
quickdiagrams/gtkclient/test.pyc
quickdiagrams/gtkclient/ui.glade
quickdiagrams/gtkclient/images/applications-development.png
quickdiagrams/gtkclient/images/applications-graphics.png
quickdiagrams/gtkclient/images/dialog-error.png
quickdiagrams/gtkclient/images/dialog-information.png
quickdiagrams/gtkclient/images/dialog-warning.png
quickdiagrams/gtkclient/images/document-open.png
quickdiagrams/gtkclient/images/edit-redo.png
quickdiagrams/gtkclient/images/edit-undo.png
quickdiagrams/gtkclient/images/media-floppy.png
quickdiagrams/gtkclient/images/status_warning.png