Metadata-Version: 1.0
Name: quickdiagrams
Version: 0.3
Summary: A text-to-class_diagram conversion tool.
Home-page: UNKNOWN
Author: Hugo Ruscitti
Author-email: hugoruscitti@gmail.com
License: UNKNOWN
Platform: UNKNOWN
